{
	"MAGIC_SUGAR": {
		"item": "sugar",
		"template": "ITEM",
		"data": 4000
	},
	"MAGIC_LUMP_1": {
		"id": "magical_lump1",
		"item": "gold_nugget",
		"template": "ITEM",
		"data": 4000
	},
	"MAGIC_LUMP_2": {
		"id": "magical_lump2",
		"item": "gold_nugget",
		"template": "ITEM",
		"data": 4001
	},
	"MAGIC_LUMP_3": {
		"id": "magical_lump3",
		"item": "gold_nugget",
		"template": "ITEM",
		"data": 4002
	},
	"ENDER_LUMP_1": {
		"id": "ender_lump1",
		"item": "gold_nugget",
		"template": "ITEM",
		"data": 4003
	},
	"ENDER_LUMP_2": {
		"id": "ender_lump2",
		"item": "gold_nugget",
		"template": "ITEM",
		"data": 4004
	},
	"ENDER_LUMP_3": {
		"id": "ender_lump3",
		"item": "gold_nugget",
		"template": "ITEM",
		"data": 4005
	},
	"BEEF_JERKY": {
		"item": "cooked_beef",
		"template": "ITEM",
		"data": 4000
	},
	"CHICKEN_JERKY": {
		"item": "cooked_chicken",
		"template": "ITEM",
		"data": 4000
	},
	"PORK_JERKY": {
		"item": "cooked_porkchop",
		"template": "ITEM",
		"data": 4000
	},
	"MUTTON_JERKY": {
		"item": "cooked_mutton",
		"template": "ITEM",
		"data": 4000
	},
	"RABBIT_JERKY": {
		"item": "cooked_rabbit",
		"template": "ITEM",
		"data": 4000
	},
	"FISH_JERKY": {
		"item": "cooked_cod",
		"template": "ITEM",
		"data": 4000
	},
	"MONSTER_JERKY": {
		"item": "rotten_flesh",
		"template": "ITEM",
		"data": 4000
	},
	"SALT": {
		"item": "sugar",
		"template": "ITEM",
		"data": 4000
	},
	"DIET_COOKIE": {
		"item": "cookie",
		"template": "ITEM",
		"data": 4000
	},
	"FORTUNE_COOKIE": {
		"item": "cookie",
		"template": "ITEM",
		"data": 4001
	},
	"MAGICAL_BOOK_COVER": {
		"item": "paper",
		"template": "ITEM",
		"data": 4000
	},
	"GOLD_PAN": {
		"item": "bowl",
		"template": "ITEM",
		"data": 4000
	},
	"ZINC_INGOT": {
		"item": "iron_ingot",
		"template": "ITEM",
		"data": 4000
	},
	"SILVER_INGOT": {
		"item": "iron_ingot",
		"template": "ITEM",
		"data": 4001
	},
	"ALUMINUM_INGOT": {
		"item": "iron_ingot",
		"template": "ITEM",
		"data": 4002
	},
	"LEAD_INGOT": {
		"item": "iron_ingot",
		"template": "ITEM",
		"data": 4003
	},
	"TIN_INGOT": {
		"item": "iron_ingot",
		"template": "ITEM",
		"data": 4004
	},
	"COPPER_INGOT": {
		"item": "brick",
		"template": "ITEM",
		"data": 4000
	},
	"NICKEL_INGOT": {
		"item": "iron_ingot",
		"template": "ITEM",
		"data": 4005
	},
	"COBALT_INGOT": {
		"item": "iron_ingot",
		"template": "ITEM",
		"data": 4006
	},
	"COPPER_WIRE": {
		"item": "string",
		"template": "ITEM",
		"data": 4000
	},
	"REDSTONE_ALLOY": {
		"id": "redstone_alloy_ingot",
		"item": "brick",
		"template": "ITEM",
		"data": 4001
	},
	"FERROSILICON": {
		"item": "iron_ingot",
		"template": "ITEM",
		"data": 4007
	},
	"GILDED_IRON": {
		"id": "gilded_iron_ingot",
		"item": "gold_ingot",
		"template": "ITEM",
		"data": 4000
	},
	"SULFATE": {
		"item": "glowstone_dust",
		"template": "ITEM",
		"data": 4000
	},
	"MAGNESIUM_INGOT": {
		"item": "iron_ingot",
		"template": "ITEM",
		"data": 4008
	},
	"SIFTED_ORE": {
		"item": "gunpowder",
		"template": "ITEM",
		"data": 4000
	},
	"CLOTH": {
		"item": "paper",
		"template": "ITEM",
		"data": 4001
	},
	"GRANDMAS_WALKING_STICK": {
		"item": "stick",
		"template": "ITEM",
		"data": 4000
	},
	"GRANDPAS_WALKING_STICK": {
		"item": "stick",
		"template": "ITEM",
		"data": 4001
	},
	"ESSENCE_OF_AFTERLIFE": {
		"item": "gunpowder",
		"template": "ITEM",
		"data": 4001
	},
	"SILICON": {
		"item": "firework_star",
		"template": "FIREWORK_STAR",
		"data": 4000
	},
	"CARBONADO": {
		"item": "player_head",
		"template": "SKULL",
		"data": 4000
	},
	"RAW_CARBONADO": {
		"item": "player_head",
		"template": "SKULL",
		"data": 4001
	}
}